LICENSE
README.md
pyproject.toml
urlblob/__init__.py
urlblob/blob.py
urlblob/common.py
urlblob/error.py
urlblob/main.py
urlblob/manager.py
urlblob/stat.py
urlblob/sync.py
urlblob/util.py
urlblob-0.1.1.dist-info/METADATA
urlblob-0.1.1.dist-info/WHEEL
urlblob-0.1.1.dist-info/entry_points.txt
urlblob-0.1.1.dist-info/licenses/LICENSE
urlblob-0.1.1.dist-info/RECORD
