Metadata-Version: 2.4
Name: urlblob
Version: 0.1.1
Summary: Agnostic access for presigned URLs at different cloud providers
Author-email: Maren van Otterdijk <maren@scidonia.ai>
Maintainer-email: Scidonia Limited <team@scidonia.com>
License: Apache-2.0
License-File: LICENSE
Keywords: azure,blob storage,cloud storage,gcs,object storage,presigned urls,s3,signed urls
Classifier: Development Status :: 3 - Alpha
Classifier: Intended Audience :: Developers
Classifier: License :: OSI Approved :: Apache Software License
Classifier: Programming Language :: Python :: 3
Classifier: Programming Language :: Python :: 3.10
Classifier: Programming Language :: Python :: 3.11
Classifier: Programming Language :: Python :: 3.12
Classifier: Topic :: Internet
Classifier: Topic :: Internet :: WWW/HTTP
Classifier: Topic :: Utilities
Classifier: Typing :: Typed
Requires-Python: >=3.10
Requires-Dist: httpx[http2]>=0.28.1
Requires-Dist: pydantic>=2.11.4
Provides-Extra: cli
Requires-Dist: rich>=14.0.0; extra == 'cli'
Requires-Dist: typer>=0.15.4; extra == 'cli'
